swas/__init__.py
swas/info.py
swas.py-0.0.5.dist-info/LICENSE
swas.py-0.0.5.dist-info/METADATA
swas.py-0.0.5.dist-info/WHEEL
swas.py-0.0.5.dist-info/top_level.txt
swas.py-0.0.5.dist-info/RECORD
