Metadata-Version: 2.1
Name: swas.py
Version: 0.0.5
Summary: a joke library made for a discord user
Home-page: https://github.com/mossyegghead01/swas.py
Author: mossy the made guy
License: MIT
Platform: UNKNOWN
